[
  {
    "id": "gf34sezvoh6",
    "name": "Leanne Graham",
    "username": "Bret",
    "email": "Sincere@april.biz"
  },
  {
    "id": "zbb6cc3ay",
    "name": "Ervin Howell",
    "username": "Antonette",
    "email": "Shanna@melissa.tv"
  },
  {
    "id": "3ay26omrd",
    "name": "Patricia Lebsack",
    "username": "Karianne",
    "email": "Julianne.OConner@kory.org"
  },
  {
    "id": "lljjmo3f3",
    "name": "Chelsey Dietrich",
    "username": "Kamren",
    "email": "Lucio_Hettinger@annie.ca"
  },
  {
    "id": "6bcc16f5-00a0-4bf2-9fec-e4bf4d8f0413",
    "name": "Diallo",
    "username": "Samba",
    "email": "sambabhouria@gmail.com"
  }
]
